AllInOneInstagramBot/__init__.py
AllInOneInstagramBot/__main__.py
AllInOneInstagramBot/version.py
AllInOneInstagramBot/core/__init__.py
AllInOneInstagramBot/core/bot_flow.py
AllInOneInstagramBot/core/config.py
AllInOneInstagramBot/core/decorators.py
AllInOneInstagramBot/core/device_facade.py
AllInOneInstagramBot/core/download_from_github.py
AllInOneInstagramBot/core/filter.py
AllInOneInstagramBot/core/handle_sources.py
AllInOneInstagramBot/core/interaction.py
AllInOneInstagramBot/core/log.py
AllInOneInstagramBot/core/navigation.py
AllInOneInstagramBot/core/persistent_list.py
AllInOneInstagramBot/core/plugin_loader.py
AllInOneInstagramBot/core/report.py
AllInOneInstagramBot/core/resources.py
AllInOneInstagramBot/core/scroll_end_detector.py
AllInOneInstagramBot/core/session_state.py
AllInOneInstagramBot/core/storage.py
AllInOneInstagramBot/core/utils.py
AllInOneInstagramBot/core/views.py
AllInOneInstagramBot/plugins/__init__.py
AllInOneInstagramBot/plugins/action_unfollow_followers.py
AllInOneInstagramBot/plugins/cloned_app.py
AllInOneInstagramBot/plugins/core_arguments.py
AllInOneInstagramBot/plugins/data_analytics.py
AllInOneInstagramBot/plugins/interact_blogger.py
AllInOneInstagramBot/plugins/interact_blogger_followers.py
AllInOneInstagramBot/plugins/interact_blogger_post_likers.py
AllInOneInstagramBot/plugins/interact_feed.py
AllInOneInstagramBot/plugins/interact_hashtag_likers.py
AllInOneInstagramBot/plugins/interact_hashtag_posts.py
AllInOneInstagramBot/plugins/interact_place_likers.py
AllInOneInstagramBot/plugins/interact_place_posts.py
AllInOneInstagramBot/plugins/like_from_urls.py
AllInOneInstagramBot/plugins/telegram.py
allinoneinstagrambot-3.1.5.dist-info/LICENSE
allinoneinstagrambot-3.1.5.dist-info/METADATA
allinoneinstagrambot-3.1.5.dist-info/WHEEL
allinoneinstagrambot-3.1.5.dist-info/entry_points.txt
allinoneinstagrambot-3.1.5.dist-info/top_level.txt
allinoneinstagrambot-3.1.5.dist-info/RECORD
